merkle_drop/__init__.py
merkle_drop/airdrop.py
merkle_drop/cli.py
merkle_drop/contracts.json
merkle_drop/deploy.py
merkle_drop/load_csv.py
merkle_drop/merkle_tree.py
merkle_drop/server.py
merkle_drop/status.py
merkle_drop-1.0.1.dist-info/LICENSE
merkle_drop-1.0.1.dist-info/METADATA
merkle_drop-1.0.1.dist-info/WHEEL
merkle_drop-1.0.1.dist-info/entry_points.txt
merkle_drop-1.0.1.dist-info/top_level.txt
merkle_drop-1.0.1.dist-info/RECORD
